ralsei/__init__.py
ralsei/app/__init__.py
ralsei/app/_decorators.py
ralsei/app/_opener.py
ralsei/app/_parsers.py
ralsei/app/_rich.py
ralsei/connection/__init__.py
ralsei/connection/_length_hint.py
ralsei/connection/create.py
ralsei/connection/ext.py
ralsei/connection/jinja.py
ralsei/console.py
ralsei/contextmanagers.py
ralsei/db_actions.py
ralsei/dialect.py
ralsei/graph/__init__.py
ralsei/graph/_flattened.py
ralsei/graph/_resolver.py
ralsei/graph/dag.py
ralsei/graph/error.py
ralsei/graph/outputof.py
ralsei/graph/path.py
ralsei/graph/pipeline.py
ralsei/graph/resolver_context.py
ralsei/graph/sequence.py
ralsei/jinja/__init__.py
ralsei/jinja/_compiler.py
ralsei/jinja/_extensions.py
ralsei/jinja/_runtime.py
ralsei/jinja/adapter.py
ralsei/jinja/environment.py
ralsei/jinja/interface.py
ralsei/jinja/wrapper.py
ralsei/py.typed
ralsei/task/__init__.py
ralsei/task/add_columns.py
ralsei/task/add_columns_sql.py
ralsei/task/base.py
ralsei/task/create_table.py
ralsei/task/create_table_sql.py
ralsei/task/map_to_new_columns.py
ralsei/task/map_to_new_table.py
ralsei/task/rowcontext.py
ralsei/types/__init__.py
ralsei/types/column.py
ralsei/types/primitives.py
ralsei/types/to_sql.py
ralsei/types/value_column.py
ralsei/utils.py
ralsei/wrappers.py
ralsei-3.2.0.dist-info/LICENSE
ralsei-3.2.0.dist-info/METADATA
ralsei-3.2.0.dist-info/WHEEL
ralsei-3.2.0.dist-info/RECORD
