Metadata-Version: 2.1
Name: ralsei
Version: 3.2.0
Summary: Build modular data pipelines running inside the postgres database
License: Apache-2.0
Author: snorkysnark
Author-email: snorkysnark@gmail.com
Requires-Python: >=3.12,<4.0
Classifier: License :: OSI Approved :: Apache Software License
Classifier: Programming Language :: Python :: 3
Classifier: Programming Language :: Python :: 3.12
Classifier: Programming Language :: Python :: 3.13
Requires-Dist: click (>=8.1.7,<9.0.0)
Requires-Dist: graphviz (>=0.20.1,<0.21.0)
Requires-Dist: jinja2 (>=3.1.3,<4.0.0)
Requires-Dist: returns (>=0.22.0,<0.23.0)
Requires-Dist: rich (>=12.5.1,<13.0.0)
Requires-Dist: sqlalchemy (>=2.0.19,<3.0.0)
